pydorm/__init__.py
pydorm/_condition.py
pydorm/_context.py
pydorm/_data_source_storage.py
pydorm/_delete.py
pydorm/_delete_wrapper.py
pydorm/_dorm.py
pydorm/_initializer.py
pydorm/_insert.py
pydorm/_insert_wrapper.py
pydorm/_middlewares.py
pydorm/_query.py
pydorm/_query_wrapper.py
pydorm/_update.py
pydorm/_update_wrapper.py
pydorm/_where.py
pydorm/protocols.py
pydorm/settings.py
pydorm/enums/__init__.py
pydorm/enums/_dialect.py
pydorm/enums/_middleware.py
pydorm/enums/_operator.py
pydorm/errors/__init__.py
pydorm/errors/_connection_exception.py
pydorm/mysql/__init__.py
pydorm/mysql/_mysql_data_source.py
pydorm/mysql/_mysql_executor.py
pydorm/mysql/_mysql_table_inspector.py
pydorm/mysql/_reusable_mysql_connection.py
pydorm/utils/__init__.py
pydorm/utils/random_utils.py
pydorm-0.10.4.dist-info/LICENSE
pydorm-0.10.4.dist-info/METADATA
pydorm-0.10.4.dist-info/WHEEL
pydorm-0.10.4.dist-info/top_level.txt
pydorm-0.10.4.dist-info/RECORD
