Metadata-Version: 2.1
Name: pydorm
Version: 0.10.4
Summary: A dynamic and lightweight Python orm framework
Author: melon
License-File: LICENSE
